{
    "clients": {
        "total": 100,
        "per_round": 20
    },
    "data": {
        "loading": "dynamic",
        "partition": {
            "size": 500
        },
        "IID": true

    },
    "federated_learning": {
        "rounds": 200,
        "target_accuracy": 0.99,
        "task": "train",
        "epochs": 4,
        "batch_size": 40
    },
    "model": "CIFAR-10",
    "method": "pow-d",
    "paths": {
        "data": "./data",
        "model": "./models"
    },
    "server": "basic"
}